Metadata-Version: 2.1
Name: AAIT25
Version: 0.0.11
Summary: Advanced Artificial Intelligence Tools is a package meant to develop and enable advanced AI functionalities in Orange Data Mining.
Home-page: 
Author: Orange community
Author-email: 
Keywords: orange3 add-on
License-File: License.txt
Requires-Dist: sentence-transformers==2.5.1
